omdrivers/CMC.py
omdrivers/Compellent.py
omdrivers/EqualLogic.py
omdrivers/F10.py
omdrivers/F10NG.py
omdrivers/FileList.py
omdrivers/MDArray.py
omdrivers/ME4.py
omdrivers/NGM.py
omdrivers/NSeries.py
omdrivers/Nagios.py
omdrivers/OME.py
omdrivers/Printer.py
omdrivers/__DellDrivers__.py
omdrivers/__init__.py
omdrivers/emcScaleIO.py
omdrivers/emcViper.py
omdrivers/iDRAC.py
omdrivers/Compellent/Compellent.Monitor
omdrivers/EqualLogic/EqualLogic.Monitor
omdrivers/F10/F10.Monitor
omdrivers/F10/__init__.py
omdrivers/F10NG/F10NG.Monitor
omdrivers/F10NG/__init__.py
omdrivers/MDArray/MDArray.Monitor
omdrivers/ME4/ME4.Monitor
omdrivers/NGM/NGM.Monitor
omdrivers/NSeries/NSeries.Monitor
omdrivers/Printer/Printer.Monitor
omdrivers/lifecycle/F10/F10Config.py
omdrivers/lifecycle/F10/__init__.py
omdrivers-1.2.490.dist-info/LICENSE
omdrivers-1.2.490.dist-info/METADATA
omdrivers-1.2.490.dist-info/WHEEL
omdrivers-1.2.490.dist-info/top_level.txt
omdrivers-1.2.490.dist-info/RECORD
