Metadata-Version: 2.1
Name: omdrivers
Version: 1.2.490
Summary: Dell OpenManage SDK
Home-page: https://support.dell.com
Author: Vaideeswaran Ganesan
Author-email: vaideeswaran_ganesan@dell.com
License: Apache Software License
Keywords: dellomsdk,dellsdk,dell,idrac,force10
Platform: UNKNOWN
Classifier: Development Status :: 5 - Production/Stable
Classifier: Intended Audience :: Developers
Classifier: Topic :: Software Development :: Build Tools
Classifier: License :: OSI Approved :: Apache Software License
Classifier: Programming Language :: Python :: 2
Classifier: Programming Language :: Python :: 3
Requires-Dist: omsdk (>=0)
